{"nodes":[{"id":"main_memory","label":"memory.ts","file_type":"code","source_file":"C:\\Users\\CoreX\\.gemini\\antigravity\\scratch\\bron-main\\src\\main\\memory.ts","source_location":"L1"},{"id":"main_memory_savedb","label":"saveDb()","file_type":"code","source_file":"C:\\Users\\CoreX\\.gemini\\antigravity\\scratch\\bron-main\\src\\main\\memory.ts","source_location":"L17"},{"id":"main_memory_initdatabase","label":"initDatabase()","file_type":"code","source_file":"C:\\Users\\CoreX\\.gemini\\antigravity\\scratch\\bron-main\\src\\main\\memory.ts","source_location":"L24"},{"id":"main_memory_getchatsessions","label":"getChatSessions()","file_type":"code","source_file":"C:\\Users\\CoreX\\.gemini\\antigravity\\scratch\\bron-main\\src\\main\\memory.ts","source_location":"L156"},{"id":"main_memory_getchatsession","label":"getChatSession()","file_type":"code","source_file":"C:\\Users\\CoreX\\.gemini\\antigravity\\scratch\\bron-main\\src\\main\\memory.ts","source_location":"L168"},{"id":"main_memory_savechatsession","label":"saveChatSession()","file_type":"code","source_file":"C:\\Users\\CoreX\\.gemini\\antigravity\\scratch\\bron-main\\src\\main\\memory.ts","source_location":"L181"},{"id":"main_memory_deletechatsession","label":"deleteChatSession()","file_type":"code","source_file":"C:\\Users\\CoreX\\.gemini\\antigravity\\scratch\\bron-main\\src\\main\\memory.ts","source_location":"L195"},{"id":"main_memory_getallmemories","label":"getAllMemories()","file_type":"code","source_file":"C:\\Users\\CoreX\\.gemini\\antigravity\\scratch\\bron-main\\src\\main\\memory.ts","source_location":"L202"},{"id":"main_memory_addmemory","label":"addMemory()","file_type":"code","source_file":"C:\\Users\\CoreX\\.gemini\\antigravity\\scratch\\bron-main\\src\\main\\memory.ts","source_location":"L217"},{"id":"main_memory_clearallmemories","label":"clearAllMemories()","file_type":"code","source_file":"C:\\Users\\CoreX\\.gemini\\antigravity\\scratch\\bron-main\\src\\main\\memory.ts","source_location":"L228"},{"id":"main_memory_getrelevantmemories","label":"getRelevantMemories()","file_type":"code","source_file":"C:\\Users\\CoreX\\.gemini\\antigravity\\scratch\\bron-main\\src\\main\\memory.ts","source_location":"L233"},{"id":"main_memory_createtask","label":"createTask()","file_type":"code","source_file":"C:\\Users\\CoreX\\.gemini\\antigravity\\scratch\\bron-main\\src\\main\\memory.ts","source_location":"L284"},{"id":"main_memory_updatetaskstatus","label":"updateTaskStatus()","file_type":"code","source_file":"C:\\Users\\CoreX\\.gemini\\antigravity\\scratch\\bron-main\\src\\main\\memory.ts","source_location":"L291"},{"id":"main_memory_addstep","label":"addStep()","file_type":"code","source_file":"C:\\Users\\CoreX\\.gemini\\antigravity\\scratch\\bron-main\\src\\main\\memory.ts","source_location":"L298"},{"id":"main_memory_addcreditusage","label":"addCreditUsage()","file_type":"code","source_file":"C:\\Users\\CoreX\\.gemini\\antigravity\\scratch\\bron-main\\src\\main\\memory.ts","source_location":"L313"},{"id":"main_memory_getcreditusagehistory","label":"getCreditUsageHistory()","file_type":"code","source_file":"C:\\Users\\CoreX\\.gemini\\antigravity\\scratch\\bron-main\\src\\main\\memory.ts","source_location":"L349"},{"id":"main_memory_getsettings","label":"getSettings()","file_type":"code","source_file":"C:\\Users\\CoreX\\.gemini\\antigravity\\scratch\\bron-main\\src\\main\\memory.ts","source_location":"L376"},{"id":"main_memory_savesettings","label":"saveSettings()","file_type":"code","source_file":"C:\\Users\\CoreX\\.gemini\\antigravity\\scratch\\bron-main\\src\\main\\memory.ts","source_location":"L408"},{"id":"main_memory_addhistoryentry","label":"addHistoryEntry()","file_type":"code","source_file":"C:\\Users\\CoreX\\.gemini\\antigravity\\scratch\\bron-main\\src\\main\\memory.ts","source_location":"L419"},{"id":"main_memory_gethistory","label":"getHistory()","file_type":"code","source_file":"C:\\Users\\CoreX\\.gemini\\antigravity\\scratch\\bron-main\\src\\main\\memory.ts","source_location":"L425"}],"edges":[{"source":"main_memory","target":"sql_js","relation":"imports_from","confidence":"EXTRACTED","source_file":"C:\\Users\\CoreX\\.gemini\\antigravity\\scratch\\bron-main\\src\\main\\memory.ts","source_location":"L1","weight":1},{"source":"main_memory","target":"path","relation":"imports_from","confidence":"EXTRACTED","source_file":"C:\\Users\\CoreX\\.gemini\\antigravity\\scratch\\bron-main\\src\\main\\memory.ts","source_location":"L2","weight":1},{"source":"main_memory","target":"fs","relation":"imports_from","confidence":"EXTRACTED","source_file":"C:\\Users\\CoreX\\.gemini\\antigravity\\scratch\\bron-main\\src\\main\\memory.ts","source_location":"L3","weight":1},{"source":"main_memory","target":"electron","relation":"imports_from","confidence":"EXTRACTED","source_file":"C:\\Users\\CoreX\\.gemini\\antigravity\\scratch\\bron-main\\src\\main\\memory.ts","source_location":"L4","weight":1},{"source":"main_memory","target":"c_users_corex_gemini_antigravity_scratch_bron_main_src_shared_types_ts","relation":"imports_from","confidence":"EXTRACTED","source_file":"C:\\Users\\CoreX\\.gemini\\antigravity\\scratch\\bron-main\\src\\main\\memory.ts","source_location":"L5","weight":1},{"source":"main_memory","target":"main_memory_savedb","relation":"contains","confidence":"EXTRACTED","source_file":"C:\\Users\\CoreX\\.gemini\\antigravity\\scratch\\bron-main\\src\\main\\memory.ts","source_location":"L17","weight":1},{"source":"main_memory","target":"main_memory_initdatabase","relation":"contains","confidence":"EXTRACTED","source_file":"C:\\Users\\CoreX\\.gemini\\antigravity\\scratch\\bron-main\\src\\main\\memory.ts","source_location":"L24","weight":1},{"source":"main_memory","target":"main_memory_getchatsessions","relation":"contains","confidence":"EXTRACTED","source_file":"C:\\Users\\CoreX\\.gemini\\antigravity\\scratch\\bron-main\\src\\main\\memory.ts","source_location":"L156","weight":1},{"source":"main_memory","target":"main_memory_getchatsession","relation":"contains","confidence":"EXTRACTED","source_file":"C:\\Users\\CoreX\\.gemini\\antigravity\\scratch\\bron-main\\src\\main\\memory.ts","source_location":"L168","weight":1},{"source":"main_memory","target":"main_memory_savechatsession","relation":"contains","confidence":"EXTRACTED","source_file":"C:\\Users\\CoreX\\.gemini\\antigravity\\scratch\\bron-main\\src\\main\\memory.ts","source_location":"L181","weight":1},{"source":"main_memory","target":"main_memory_deletechatsession","relation":"contains","confidence":"EXTRACTED","source_file":"C:\\Users\\CoreX\\.gemini\\antigravity\\scratch\\bron-main\\src\\main\\memory.ts","source_location":"L195","weight":1},{"source":"main_memory","target":"main_memory_getallmemories","relation":"contains","confidence":"EXTRACTED","source_file":"C:\\Users\\CoreX\\.gemini\\antigravity\\scratch\\bron-main\\src\\main\\memory.ts","source_location":"L202","weight":1},{"source":"main_memory","target":"main_memory_addmemory","relation":"contains","confidence":"EXTRACTED","source_file":"C:\\Users\\CoreX\\.gemini\\antigravity\\scratch\\bron-main\\src\\main\\memory.ts","source_location":"L217","weight":1},{"source":"main_memory","target":"main_memory_clearallmemories","relation":"contains","confidence":"EXTRACTED","source_file":"C:\\Users\\CoreX\\.gemini\\antigravity\\scratch\\bron-main\\src\\main\\memory.ts","source_location":"L228","weight":1},{"source":"main_memory","target":"main_memory_getrelevantmemories","relation":"contains","confidence":"EXTRACTED","source_file":"C:\\Users\\CoreX\\.gemini\\antigravity\\scratch\\bron-main\\src\\main\\memory.ts","source_location":"L233","weight":1},{"source":"main_memory","target":"main_memory_createtask","relation":"contains","confidence":"EXTRACTED","source_file":"C:\\Users\\CoreX\\.gemini\\antigravity\\scratch\\bron-main\\src\\main\\memory.ts","source_location":"L284","weight":1},{"source":"main_memory","target":"main_memory_updatetaskstatus","relation":"contains","confidence":"EXTRACTED","source_file":"C:\\Users\\CoreX\\.gemini\\antigravity\\scratch\\bron-main\\src\\main\\memory.ts","source_location":"L291","weight":1},{"source":"main_memory","target":"main_memory_addstep","relation":"contains","confidence":"EXTRACTED","source_file":"C:\\Users\\CoreX\\.gemini\\antigravity\\scratch\\bron-main\\src\\main\\memory.ts","source_location":"L298","weight":1},{"source":"main_memory","target":"main_memory_addcreditusage","relation":"contains","confidence":"EXTRACTED","source_file":"C:\\Users\\CoreX\\.gemini\\antigravity\\scratch\\bron-main\\src\\main\\memory.ts","source_location":"L313","weight":1},{"source":"main_memory","target":"main_memory_getcreditusagehistory","relation":"contains","confidence":"EXTRACTED","source_file":"C:\\Users\\CoreX\\.gemini\\antigravity\\scratch\\bron-main\\src\\main\\memory.ts","source_location":"L349","weight":1},{"source":"main_memory","target":"main_memory_getsettings","relation":"contains","confidence":"EXTRACTED","source_file":"C:\\Users\\CoreX\\.gemini\\antigravity\\scratch\\bron-main\\src\\main\\memory.ts","source_location":"L376","weight":1},{"source":"main_memory","target":"main_memory_savesettings","relation":"contains","confidence":"EXTRACTED","source_file":"C:\\Users\\CoreX\\.gemini\\antigravity\\scratch\\bron-main\\src\\main\\memory.ts","source_location":"L408","weight":1},{"source":"main_memory","target":"main_memory_addhistoryentry","relation":"contains","confidence":"EXTRACTED","source_file":"C:\\Users\\CoreX\\.gemini\\antigravity\\scratch\\bron-main\\src\\main\\memory.ts","source_location":"L419","weight":1},{"source":"main_memory","target":"main_memory_gethistory","relation":"contains","confidence":"EXTRACTED","source_file":"C:\\Users\\CoreX\\.gemini\\antigravity\\scratch\\bron-main\\src\\main\\memory.ts","source_location":"L425","weight":1},{"source":"main_memory_initdatabase","target":"main_memory_savedb","relation":"calls","confidence":"EXTRACTED","source_file":"C:\\Users\\CoreX\\.gemini\\antigravity\\scratch\\bron-main\\src\\main\\memory.ts","source_location":"L148","weight":1},{"source":"main_memory_savechatsession","target":"main_memory_savedb","relation":"calls","confidence":"EXTRACTED","source_file":"C:\\Users\\CoreX\\.gemini\\antigravity\\scratch\\bron-main\\src\\main\\memory.ts","source_location":"L185","weight":1},{"source":"main_memory_deletechatsession","target":"main_memory_savedb","relation":"calls","confidence":"EXTRACTED","source_file":"C:\\Users\\CoreX\\.gemini\\antigravity\\scratch\\bron-main\\src\\main\\memory.ts","source_location":"L197","weight":1},{"source":"main_memory_addmemory","target":"main_memory_savedb","relation":"calls","confidence":"EXTRACTED","source_file":"C:\\Users\\CoreX\\.gemini\\antigravity\\scratch\\bron-main\\src\\main\\memory.ts","source_location":"L225","weight":1},{"source":"main_memory_clearallmemories","target":"main_memory_savedb","relation":"calls","confidence":"EXTRACTED","source_file":"C:\\Users\\CoreX\\.gemini\\antigravity\\scratch\\bron-main\\src\\main\\memory.ts","source_location":"L230","weight":1},{"source":"main_memory_createtask","target":"main_memory_savedb","relation":"calls","confidence":"EXTRACTED","source_file":"C:\\Users\\CoreX\\.gemini\\antigravity\\scratch\\bron-main\\src\\main\\memory.ts","source_location":"L287","weight":1},{"source":"main_memory_updatetaskstatus","target":"main_memory_savedb","relation":"calls","confidence":"EXTRACTED","source_file":"C:\\Users\\CoreX\\.gemini\\antigravity\\scratch\\bron-main\\src\\main\\memory.ts","source_location":"L293","weight":1},{"source":"main_memory_addstep","target":"main_memory_savedb","relation":"calls","confidence":"EXTRACTED","source_file":"C:\\Users\\CoreX\\.gemini\\antigravity\\scratch\\bron-main\\src\\main\\memory.ts","source_location":"L310","weight":1},{"source":"main_memory_addcreditusage","target":"main_memory_savedb","relation":"calls","confidence":"EXTRACTED","source_file":"C:\\Users\\CoreX\\.gemini\\antigravity\\scratch\\bron-main\\src\\main\\memory.ts","source_location":"L346","weight":1},{"source":"main_memory_savesettings","target":"main_memory_savedb","relation":"calls","confidence":"EXTRACTED","source_file":"C:\\Users\\CoreX\\.gemini\\antigravity\\scratch\\bron-main\\src\\main\\memory.ts","source_location":"L415","weight":1},{"source":"main_memory_addhistoryentry","target":"main_memory_savedb","relation":"calls","confidence":"EXTRACTED","source_file":"C:\\Users\\CoreX\\.gemini\\antigravity\\scratch\\bron-main\\src\\main\\memory.ts","source_location":"L422","weight":1}]}